ezmsg/websocket/__init__.py
ezmsg/websocket/__version__.py
ezmsg/websocket/units.py
ezmsg_websocket-1.1.3.dist-info/METADATA
ezmsg_websocket-1.1.3.dist-info/WHEEL
ezmsg_websocket-1.1.3.dist-info/licenses/LICENSE
ezmsg_websocket-1.1.3.dist-info/RECORD
