Metadata-Version: 2.4
Name: ezmsg-websocket
Version: 1.1.3
Summary: Websocket server and client units for ezmsg
Author-email: Griffin Milsap <griffin.milsap@gmail.com>, Preston Peranich <pperanich@gmail.com>
License-Expression: MIT
License-File: LICENSE
Requires-Python: >=3.10
Requires-Dist: ezmsg>=3.6.0
Requires-Dist: websockets>=8.1
